{
  "source": {
    "type": "youtube",
    "channel": "은현장의 골목식당",
    "title": "장사의신 출연후 빚2억 숨긴거 여자친구에게 걸린 사장님",
    "url": null,
    "published_date": null,
    "language": "ko",
    "has_cc": true
  },
  "context": {
    "market_type": ["신도시 미사","주거밀집","역세권"],
    "category": ["수제버거","양식","퓨전"],
    "customer_segment": ["20~30대 연인","가족단위","근처 직장인/거주민"],
    "channel": ["네이버플레이스","인스타/릴스","틱톡","배달앱"],
    "task": ["마케팅효율극대화","브랜딩차별화","재방문율상승","검색노출강화"],
    "constraints": ["높은부채(2억)","고정비부담","브랜드인지도제한","1인중심운영"]
  },
  "problem": [
    "방송 출연 효과로 단기 매출 급증했으나 장기적 브랜딩/마케팅 구조 미흡",
    "SNS·플레이스 노출 관리 부족 → 검색 노출량은 오르지만 리뷰/전환율 한계",
    "세트 메뉴 할인폭 낮아 클릭·주문 유인력이 약함",
    "신메뉴(콘피자 등)는 반응 좋으나 일부 메뉴는 가격 대비 만족도 낮음",
    "매출은 오르지만 부채 상환 부담 지속 → 현금흐름 압박"
  ],
  "solution": [
    "① 검색 기반 마케팅: ‘미사 맛집·미사 버거·미사 스테이크’ 등 **지역 키워드 광고+릴스** 동시 운영. 검색량 상승을 지속 모니터링하며 ROAS 검증.",
    "② 리뷰/UGC 활성화: 매장 내 리뷰 이벤트 POP 설치. **영수증 리뷰→음료 무료**, 포토 리뷰→소스/사이드 증정. 눈에 보이는 위치에 반복 노출.",
    "③ 세트 메뉴 개편: 할인폭 단계화(A세트 6천 할인·B세트 4천·C세트 2천). 고객이 단품 대신 세트를 ‘이득’으로 인식하도록 앵커링.",
    "④ 릴스/틱톡 숏폼 전략: ‘첫번째 레슨 비스트롱 가기, 두번째 레슨 시그니처 먹기’ 형식으로 숏폼 밈화. 직원 참여·고객 참여 영상으로 콘텐츠 풀 확대.",
    "⑤ 시그니처 강화: 콘피자/버거+스테이크를 ‘투톱’으로 브랜딩. SNS·간판·메뉴판에 ‘비스트롱=콘피자 버거집’ 명확히 각인.",
    "⑥ 배달 최적화: 홀 중심이지만 배달앱 전용 메뉴(버거 단품+사이드 패키지) 구성. 리뷰쿠폰(1천원)→2회차 재주문 전용.",
    "⑦ KPI 관리: 월 검색량, 세트판매비중(≥45%), 리뷰수 증감, 배달 매출 비중(≥20%)을 대시보드화. 광고비 100만→검색노출 300만 효과 검증."
  ],
  "how_to": [
    "네이버 플레이스 상단 메뉴 사진 교체(시그니처 중심 3컷)",
    "리뷰 이벤트 POP 설치(입구·테이블·카운터)",
    "세트 메뉴 할인 단계화 및 키오스크 상단 배치",
    "주 3회 릴스/틱톡 업로드(레슨형 숏폼+메뉴 비주얼)",
    "콘피자·스테이크 시식 영상 촬영 후 광고 전환",
    "배달앱 전용 메뉴 런칭 및 리뷰쿠폰 설정",
    "검색량→매출 연동 KPI 대시보드 작성"
  ],
  "checklist": [
    "□ 키워드 광고 및 릴스 병행 세팅",
    "□ 리뷰 이벤트 POP 설치",
    "□ 세트메뉴 할인폭 조정",
    "□ 릴스/틱톡 숏폼 주3회 업로드",
    "□ 콘피자/스테이크 브랜딩 강화",
    "□ 배달앱 전용메뉴+리뷰쿠폰 설정",
    "□ KPI 대시보드 제작"
  ],
  "evidence": [
    {
      "quote": "플레이스 검색량이 400에서 1,100 이상으로 증가하며 매출이 우상향.",
      "timecode": null
    },
    {
      "quote": "세트 메뉴 할인폭이 작아 클릭·선택 메리트 부족, ‘단품으로 간다’는 지적.",
      "timecode": null
    },
    {
      "quote": "릴스/인스타 영상 노출로 신규 유입 효과 체감.",
      "timecode": null
    }
  ],
  "caveats": [
    "세트 할인폭 과다 시 원가율 악화",
    "릴스/틱톡 콘텐츠 퀄리티가 낮으면 브랜드 신뢰도 하락",
    "검색광고 효율이 낮으면 광고비 낭비 리스크"
  ],
  "expected_effect": "검색량-매출 상관관계 강화로 월매출 2,700만→3,500만 안정화, 세트판매비중 45% 이상 확보, 리뷰·UGC 확산으로 신규고객 유입 증대. SNS 숏폼 밈화로 지역 내 ‘비스트롱=콘피자 버거집’ 브랜딩 확립.",
  "confidence": 0.88
}
